Workbook

Sheet Inputs
A1: Retail Relative Valuation 2025 Financial year– Inputs
A3: Assumptions
A4: Market price date | B4: 45717
B5: 1 March 2025 was a Saturday. So we use immediately preceding JSE trading day close for all prices, 28 February 2025.
A7: FY2025 Financial Statement Inputs and Market Prices
A8: Company | B8: Current Price (R/share) | C8: Issued Shares (m) | D8: Treasury Shares (m) | E8: Shares Outstanding (m) | F8: Revenue (Rm) | G8: EBIT / Operating Profit (Rm) | H8: D&A / EBITDA Add-backs (Rm) | I8: EBITDA Used (Rm) | J8: Borrowings & Overdrafts (Rm) | K8: Lease Liabilities (Rm) | L8: Cash & Equivalents (Rm) | M8: Headline Earnings Per Share(HEPS) Used (R/share) | N8: Source For values
A9: Pick n Pay | B9: 28.15 | C9: 745.65713 | D9: 9.945788 | E9: =C9-D9 -> 735.71134 | F9: 122124 | G9: 1759 | H9: 3894 | I9: 5653 | J9: 1150 | K9: 19120 | L9: 5328 | M9: -0.6154 | N9: Pick n Pay Integrated Annual Report 2025: EBITDA is the report's IFRS 16 EBITDA.
A10: Shoprite | B10: 275.01 | C10: 591.3385 | D10: 50.815502 | E10: =C10-D10 -> 540.523 | F10: 256682 | G10: 14943 | H10: 9067 | I10: =G10+H10 -> 24010 | J10: 8856 | K10: 47020 | L10: 9946 | M10: 14.316 | N10: Shoprite Holdings AFS 2025: EBITDA derived as operating profit + total D&A.
A11: Woolworths | B11: 58.24 | C11: 988.69595 | D11: 84.261465 | E11: =C11-D11 -> 904.43448 | F11: 80243 | G11: 4384 | H11: 3485 | I11: =G11+H11 -> 7869 | J11: 9854 | K11: 9816 | L11: 4291 | M11: 2.681 | N11: Woolworths Holdings AFS 2025: comprehensive income and financial position
A12: SPAR | B12: 133.09 | C12: 192.60235 | D12: 0.017689 | E12: =C12-D12 -> 192.58467 | F12: 131457.7 | G12: 1983.5 | H12: 1134.6 | I12: =G12+H12 -> 3118.1 | J12: 7727.5 | K12: 8537.6 | L12: 2752.6 | M12: 7.689 | N12: SPAR Group AFS 2025: Continuing operations are used because UK and Switzerland are classified as discontinued.

Sheet EV_EBITDA
A1: EV/EBITDA Relative Valuation
A3: Metric | B3: Pick n Pay | C3: Shoprite | D3: Woolworths | E3: SPAR
A4: Current share price (R/share) | B4: =Inputs!B9 -> 28.15 | C4: =Inputs!B10 -> 275.01 | D4: =Inputs!B11 -> 58.24 | E4: =Inputs!B12 -> 133.09
A5: Shares outstanding (m) | B5: =Inputs!E9 -> 735.71134 | C5: =Inputs!E10 -> 540.523 | D5: =Inputs!E11 -> 904.43448 | E5: =Inputs!E12 -> 192.58467
A6: Market capitalisation (Rm) | B6: =B4*B5 -> 20710.274 | C6: =C4*C5 -> 148649.23 | D6: =D4*D5 -> 52674.264 | E6: =E4*E5 -> 25631.093
A7: Borrowings & overdrafts (Rm) | B7: =Inputs!J9 -> 1150 | C7: =Inputs!J10 -> 8856 | D7: =Inputs!J11 -> 9854 | E7: =Inputs!J12 -> 7727.5
A8: Lease liabilities (Rm) | B8: =Inputs!K9 -> 19120 | C8: =Inputs!K10 -> 47020 | D8: =Inputs!K11 -> 9816 | E8: =Inputs!K12 -> 8537.6
A9: Cash & cash equivalents (Rm) | B9: =Inputs!L9 -> 5328 | C9: =Inputs!L10 -> 9946 | D9: =Inputs!L11 -> 4291 | E9: =Inputs!L12 -> 2752.6
A10: Net debt (Rm) | B10: =B7+B8-B9 -> 14942 | C10: =C7+C8-C9 -> 45930 | D10: =D7+D8-D9 -> 15379 | E10: =E7+E8-E9 -> 13512.5
A11: Enterprise value (Rm) | B11: =B6+B10 -> 35652.274 | C11: =C6+C10 -> 194579.23 | D11: =D6+D10 -> 68053.264 | E11: =E6+E10 -> 39143.593
A12: EBITDA (Rm) | B12: =Inputs!I9 -> 5653 | C12: =Inputs!I10 -> 24010 | D12: =Inputs!I11 -> 7869 | E12: =Inputs!I12 -> 3118.1
A13: EV/EBITDA | B13: =B11/B12 -> 6.3067883 | C13: =C11/C12 -> 8.1040912 | D13: =D11/D12 -> 8.6482735 | E13: =E11/E12 -> 12.553668
A14: Peer EV/EBITDA | B14: =AVERAGE(C13:E13) -> 9.7686777 | C14: =AVERAGE(B13,D13,E13) -> 9.1695767 | D14: =AVERAGE(B13,C13,E13) -> 8.9881826 | E14: =AVERAGE(B13:D13) -> 7.6863843
A15: Implied enterprise value (Rm) | B15: =B12*B14 -> 55222.335 | C15: =C12*C14 -> 220161.54 | D15: =D12*D14 -> 70728.009 | E15: =E12*E14 -> 23966.915
A16: Less: net debt (Rm) | B16: =B10 -> 14942 | C16: =C10 -> 45930 | D16: =D10 -> 15379 | E16: =E10 -> 13512.5
A17: Implied equity value (Rm) | B17: =B15-B16 -> 40280.335 | C17: =C15-C16 -> 174231.54 | D17: =D15-D16 -> 55349.009 | E17: =E15-E16 -> 10454.415
A18: Estimated value per share (R) | B18: =B17/B5 -> 54.750189 | C18: =C17/C5 -> 322.3388 | D18: =D17/D5 -> 61.197367 | E18: =E17/E5 -> 54.284774
A19: market price (R) | B19: =B4 -> 28.15 | C19: =C4 -> 275.01 | D19: =D4 -> 58.24 | E19: =E4 -> 133.09
A20: Upside / (downside) | B20: =B18/B19-1 -> 0.94494454 | C20: =C18/C19-1 -> 0.17209848 | D20: =D18/D19-1 -> 0.050778966 | E20: =E18/E19-1 -> -0.59211981
A21: Valuation indication | B21: =IF(B20>0,"Undervalued",IF(B20<0,"Overvalued","Fairly valued")) -> Undervalued | C21: =IF(C20>0,"Undervalued",IF(C20<0,"Overvalued","Fairly valued")) -> Undervalued | D21: =IF(D20>0,"Undervalued",IF(D20<0,"Overvalued","Fairly valued")) -> Undervalued | E21: =IF(E20>0,"Undervalued",IF(E20<0,"Overvalued","Fairly valued")) -> Overvalued

Sheet PE_PS
A1: P/E Valuation and Pick n Pay P/S Valuation
A3: Metric | B3: Pick n Pay | C3: Shoprite | D3: Woolworths | E3: SPAR
A4: Current share price (R/share) | B4: =Inputs!B9 -> 28.15 | C4: =Inputs!B10 -> 275.01 | D4: =Inputs!B11 -> 58.24 | E4: =Inputs!B12 -> 133.09
A5: Shares outstanding (m) | B5: =Inputs!E9 -> 735.71134 | C5: =Inputs!E10 -> 540.523 | D5: =Inputs!E11 -> 904.43448 | E5: =Inputs!E12 -> 192.58467
A6: Market capitalisation (Rm) | B6: =B4*B5 -> 20710.274 | C6: =C4*C5 -> 148649.23 | D6: =D4*D5 -> 52674.264 | E6: =E4*E5 -> 25631.093
A7: FY2025 HEPS used (R/share) | B7: =Inputs!M9 -> -0.6154 | C7: =Inputs!M10 -> 14.316 | D7: =Inputs!M11 -> 2.681 | E7: =Inputs!M12 -> 7.689
A8: P/E multiple | C8: =C4/C7 -> 19.209975 | D8: =D4/D7 -> 21.723238 | E8: =E4/E7 -> 17.309143
A9: Peer P/E multiple | C9: =AVERAGE(D8,E8) -> 19.51619 | D9: =AVERAGE(C8,E8) -> 18.259559 | E9: =AVERAGE(C8,D8) -> 20.466606
A10: P/E implied value per share (R) | C10: =C9*C7 -> 279.39378 | D10: =D9*D7 -> 48.953877 | E10: =E9*E7 -> 157.36774
A12: Revenue (Rm) | B12: =Inputs!F9 -> 122124 | C12: =Inputs!F10 -> 256682 | D12: =Inputs!F11 -> 80243 | E12: =Inputs!F12 -> 131457.7
A13: P/S multiple | B13: =B6/B12 -> 0.16958398 | C13: =C6/C12 -> 0.57911825 | D13: =D6/D12 -> 0.65643438 | E13: =E6/E12 -> 0.19497597
A14: Peer P/S multiple | B14: =AVERAGE(C13:E13) -> 0.47684287
A15: P/S implied market value (Rm) | B15: =B12*B14 -> 58233.959
A16: P/S implied value per share (R) | B16: =B15/B5 -> 79.15327
A18: Second valuation method used | B18: P/S | C18: P/E | D18: P/E | E18: P/E
A19: Second-method value per share (R) | B19: =B16 -> 79.15327 | C19: =C10 -> 279.39378 | D19: =D10 -> 48.953877 | E19: =E10 -> 157.36774

Sheet Sources
A1: Sources, Assumptions and Methodology Notes
A3: Company / Topic | B3: Input Used | C3: Source Document / Web Source
A4: Pick n Pay | B4: Revenue, EBITDA, borrowings, lease liabilities, cash shares, HEPS | C4: integrated-annual-report-2025-spread.pdf
A5: Shoprite | B5: Revenue, operating profit, Depreciation&Amortisation(D&A), debt, leases, cash, shares, HEPS | C5: shp-afs-2025.pdf
A6: Woolworths | B6: Revenue, operating profit, D&A, debt, leases, cash, shares, HEPS | C6: whlfy25.pdf
A7: SPAR | B7: Revenue, operating profit, D&A, debt, leases, cash, shares, HEPS | C7: SPAR_Group_FY25_AFS.pdf
A8: Market prices | B8: PIK R28.15; SHP R275.01; WHL R58.24; SPP R133.09 | C8: investing.com
A10: Valuation Formulas
A11: Market capitalisation | B11: Current share price × shares outstanding
A12: Net debt | B12: Borrowings + lease liabilities − cash and cash equivalents
A13: Enterprise value | B13: Market capitalisation + net debt
A14: EV/EBITDA | B14: Enterprise value ÷ EBITDA
A15: Peer EV/EBITDA | B15: Average of the other three retailers; target company excluded
A16: Implied enterprise value | B16: Target EBITDA × peer EV/EBITDA
A17: Implied equity value | B17: Implied enterprise value − target net debt
A18: Estimated value/share | B18: Implied equity value ÷ shares outstanding
A19: Peer P/E | B19: Average of the other retailers P/ (Target company exluded)
A20: P/E value/share | B20: Peer P/E × target HEPS (Shoprite, Woolworths, SPAR only)
A21: Peer P/S | B21: Average of the other retailers P/S (Target company excluded)
A22: Pick n Pay P/S value | B22: Peer P/S × Pick n Pay revenue ÷ Pick n Pay shares outstanding
A24: Important Limitations
A25: 1. This is a relative valuation, not a discounted-cash-flow valuation. 2. The valuation date is 1 March 2025. Because this date fell on a Saturday, the JSE closing prices from Friday, 28 February 2025 are used for all four retailers. 3. The results are sensitive to peer selection and to the decision to include IFRS 16 lease liabilities in net debt. 4. SPAR's discontinued operations create a comparability issue; continuing-operations EBITDA and HEPS are used to reflect the ongoing retail business. 5. A simple average of the two methods is shown on Summary only as a convenient blended indicator.
